msfabric_devops/__init__.py
msfabric_devops/api.py
msfabric_devops/authenticate.py
msfabric_devops/config.py
msfabric_devops/items.py
msfabric_devops/semantic_models.py
msfabric_devops/workspaces.py
msfabric_devops-0.2.0.dist-info/licenses/LICENSE
msfabric_devops-0.2.0.dist-info/METADATA
msfabric_devops-0.2.0.dist-info/WHEEL
msfabric_devops-0.2.0.dist-info/top_level.txt
msfabric_devops-0.2.0.dist-info/RECORD
