Metadata-Version: 2.4
Name: msfabric-devops
Version: 0.2.0
Summary: Python package to interact with Microsoft Fabric items.
Author-email: Hugo Salaun <hcrsalaun@gmail.com>
License-Expression: MIT
Requires-Python: >=3.9
License-File: LICENSE
Requires-Dist: azure-identity>=1.17
Requires-Dist: requests>=2.32
Dynamic: license-file
